{"Oregon": 6, "Washington": 4, "State of Minas Gerais": 1, "Louisiana": 14, "Kentucky": 12, "West Virginia": 3, "Oklahoma": 9, "Mississippi": 3, "Minnesota": 4, "Tennessee": 18, "Ohio": 26, "Getseman\u00ed": 1, "Karnataka": 1, "California": 70, "British Columbia": 8, "Illinois": 23, "Ontario": 5, "New Brunswick": 1, "Lima Region": 4, "Alabama": 11, "Arkansas": 5, "Hawaii": 8, "Kansas": 2, "Nevada": 6, "Texas": 78, "Iowa": 1, "New Jersey": 16, "Ober\u00f6sterreich": 1, "Haryana": 1, "South Dakota": 2, "Delaware": 2, "Colorado": 9, "Pennsylvania": 18, "Nidwalden": 1, "Scotland": 1, "Alberta": 1, "Massachusetts": 6, "Alaska": 2, "Wyoming": 1, "Florida": 81, "Mexico City": 1, "Missouri": 3, "England": 6, "Utah": 7, "Arizona": 8, "North Carolina": 14, "Victoria": 2, "Maine": 3, "South Carolina": 12, "Brussels": 1, "Maryland": 4, "Georgia": 31, "Otago": 1, "New Hampshire": 3, "Hesse": 1, "ID": 1, "Virginia": 12, "North Dakota": 1, "Connecticut": 6, "Distrito Nacional": 1, "Lazio": 1, "Vitebsk Region": 1, "New Mexico": 4, "Hauts-de-France": 6, "Michigan": 17, "Wisconsin": 8, "Indiana": 3, "District of Columbia": 18, "New York": 62, "Nebraska": 2}