{
    "VEGETTA777": {},
    "Smosh": {},
    "VitalyzdTv": {},
    "Galo Frito": {},
    "\u041c\u0430\u0448\u0430 \u0438 \u041c\u0435\u0434\u0432\u0435\u0434\u044c": {},
    "Vevo": {},
    "MattyBRaps": {},
    "Yuya": {},
    "officialpsy": {},
    "W2S": {},
    "Cyprien": {},
    "IGN": {},
    "ERB": {
        "Alexander the Great vs Ivan the Terrible - Epic Rap Battles of History Season 5": {
            "google": "18477660",
            "fb": "193k Views"
        }
    },
    "luzugames": {},
    "CanalCanalha": {},
    "FPSRussia": {},
    "ThatcherJoe": {
        "BIGGEST FAN PRANK": {
            "google": "2725758",
            "fb": "953k Views"
        }
    },
    "boyceavenue": {},
    "elrubiusOMG": {},
    "The Late Late Show with James Corden": {
        "Morris Chestnut Roasting By An Open Fire": {
            "google": "77981",
            "fb": "85k Views"
        }
    },
    "Lindsey Stirling": {
        "Lindsey Stirling - Something Wild ft. Andrew McMahon in the Wilderness (From Disney's Pete's Dragon)": {
            "google": "9005181",
            "fb": "188k Views"
        }
    },
    "Kurt Hugo Schneider": {},
    "NoCopyrightSounds": {},
    "CutiePieMarzia": {},
    "WatchMojo.com": {},
    "PrankvsPrank": {},
    "Wiz Khalifa": {},
    "FailArmy": {},
    "JoeyGraceffa": {},
    "VICE": {},
    "Unbox Therapy": {},
    "Ed Sheeran": {},
    "Ultra Music": {},
    "AuthenticGames": {},
    "SSundee": {},
    "IISuperwomanII": {
        "When A Brown Girl Dates A White Boy (ft. Adam Devine)": {
            "google": "4910247",
            "fb": "868k Views"
        }
    },
    "Porta dos Fundos": {},
    "REACT": {},
    "Rosanna Pansino": {},
    "Miranda Sings": {
        "WARHEAD CANDY CANE CHALLENGE": {
            "google": "611486",
            "fb": "1.8M Views"
        }
    },
    "KSI": {
        "EXPERIMENT Glowing 1000 degree KATANA VS 10 MILLION SUBSCRIBER PLAQUE": {
            "google": "6023473",
            "fb": "178k Views"
        }
    },
    "Tyler Oakley": {},
    "Rclbeauty101": {},
    "Ray  William Johnson": {},
    "David Guetta": {},
    "Trap Nation": {
        "Two Feet - Go F*ck Yourself": {
            "google": "1527647",
            "fb": "21k Views"
        }
    },
    "Dude Perfect": {
        "Giant Nerf Trick Shots | Dude Perfect": {
            "google": "21325009",
            "fb": "2.7M Views"
        },
        "Trampoline Charades Team Battle | Dude Perfect": {
            "google": "10910374",
            "fb": "2.7M Views"
        },
        "Giant Warship Battle | Dude Perfect": {
            "google": "18096614",
            "fb": "2.7M Views"
        },
        "Extreme Weather Golf Battle | Dude Perfect": {
            "google": "8355129",
            "fb": "2.7M Views"
        },
        "Metal Detector Battle | Dude Perfect": {
            "google": "12521954",
            "fb": "2.7M Views"
        },
        "Drone Hunting Battle | Dude Perfect": {
            "google": "14467608",
            "fb": "2.7M Views"
        },
        "Flip Edition | Dude Perfect": {
            "google": "26772638",
            "fb": "2.7M Views"
        }
    },
    "Bethany Mota": {
        "Things Girls Do Before Bed | Bethany Mota": {
            "google": "1750363",
            "fb": "299k Views"
        }
    },
    "The Tonight Show Starring Jimmy Fallon": {},
    "Zoella": {},
    "Rooster Teeth": {},
    "theRadBrad": {},
    "Wassabi Productions": {},
    "JennaMarbles": {},
    "ComedyShortsGamer": {},
    "5incominutos": {},
    "Trap City": {
        "Zay Hilfigerrr - Juju On Dat Beat (Muffin Remix)": {
            "google": "475602",
            "fb": "50k Views"
        },
        "Cymatics - Nightmares Vol. 2 for Serum (Download Link in Description)": {
            "google": "159710",
            "fb": "23k Views"
        }
    },
    "fouseyTUBE": {},
    "Skrillex": {},
    "Fernanfloo": {},
    "Ali-A": {},
    "TheWillyrex": {},
    "emimusic": {},
    "HolaSoyGerman.": {},
    "CaptainSparklez": {},
    "SMTOWN": {
        "NCT 127_Limitless_Teaser Clip# MARK 2": {
            "google": "216465",
            "fb": "85k Views"
        },
        "NCT 127_Limitless_Teaser Clip# MARK 1": {
            "google": "161553",
            "fb": "85k Views"
        },
        "NCT 127_Limitless_Teaser Clip# HAECHAN 1": {
            "google": "223408",
            "fb": "85k Views"
        },
        "NCT 127_Limitless_Teaser Clip# HAECHAN 2": {
            "google": "325445",
            "fb": "85k Views"
        }
    },
    "BuzzFeedVideo": {
        "People Eat Insects For The First Time": {
            "google": "346240",
            "fb": "101k Views"
        },
        "People Make Pinterest Christmas Treats": {
            "google": "480077",
            "fb": "230k Views"
        },
        "Couples Give Each Other Surprise Hair Makeovers \u2022 Ned & Ariel": {
            "google": "1043843",
            "fb": "1.2M Views"
        },
        "People Play \"Never Have I Ever\" With Their Parents": {
            "google": "2105535",
            "fb": "962k Views"
        },
        "Men Decorate Each Others Beards For Christmas": {
            "google": "292165",
            "fb": "230k Views"
        },
        "Growing Up With An African Mum": {
            "google": "391047",
            "fb": "530k Views"
        },
        "Adults Try '90s Infomercial Toys": {
            "google": "1304763",
            "fb": "422k Views"
        }
    },
    "League of Legends": {
        "All-Star Barcelona 2016 | Login Screen - League of Legends": {
            "google": "163865",
            "fb": "2.8M Views"
        }
    },
    "HowToBasic": {
        "How To Make a Cheeseburger Pizza": {
            "google": "3006992",
            "fb": "1.8M Views"
        },
        "How To Catch Rare Pokemon on Pokemon GO": {
            "google": "5509939",
            "fb": "9.9M Views"
        }
    },
    "Felipe Neto": {},
    "enchufetv": {
        "#EnchufeLive con Orlando Herrera": {
            "google": "150586",
            "fb": "27k Views"
        }
    },
    "Willyrex": {},
    "Bruno Mars": {},
    "GMM GRAMMY OFFICIAL": {},
    "Markiplier": {},
    "VanossGaming": {},
    "WWE": {},
    "Sky Does Minecraft": {},
    "RocketJump": {
        "Five Nights at Freddie's": {
            "google": "373542",
            "fb": "39k Views"
        }
    },
    "Michelle Phan": {},
    "RomanAtwood": {},
    "Tobuscus": {
        "iPhone 7 HD Video Test (Front-Facing Camera 7 Plus vs. 6s Plus)": {
            "google": "83573",
            "fb": "57k Views"
        },
        "TOBUSCUS LIVE (at School of Rock)": {
            "google": "40241",
            "fb": "9.2k Views"
        },
        "School of ROCK (IN REAL LIFE)": {
            "google": "40650",
            "fb": "14k Views"
        },
        "Tobuscus Adventures - AUDIOBOOK (The Puppet Show)": {
            "google": "34403",
            "fb": "21k Views"
        }
    },
    "Vsauce": {
        "ANNOUNCING BRAIN CANDY LIVE": {
            "google": "1007708",
            "fb": "25k Views"
        }
    },
    "MyLifeAsEva": {},
    "Caspar": {},
    "TheFineBros": {},
    "Linkin Park": {
        "Phoenix LIVE golfing with Brendan Steele": {
            "google": "50353",
            "fb": "270k Views"
        },
        "Studio Moments: Bongo Band Jam": {
            "google": "83762",
            "fb": "407k Views"
        },
        "Studio Views": {
            "google": "95839",
            "fb": "265k Views"
        },
        "Mannequin Challenge from \"Burn It Down\" - Linkin Park": {
            "google": "374675",
            "fb": "2.1M Views"
        }
    },
    "JuegaGerman": {},
    "Clash of Clans": {
        "Clash-A-Rama! The Series: 12 Days of Clashmas": {
            "google": "14806306",
            "fb": "1.3M Views"
        },
        "Clash-A-Rama! The Series: Hog Rider Rides Again": {
            "google": "16757432",
            "fb": "1.3M Views"
        }
    },
    "TheSyndicateProject": {},
    "CaELiKe": {},
    "Parafernalha": {},
    "Epic Meal Time": {
        "Epic LIVE Teaser": {
            "google": "17426",
            "fb": "21k Views"
        }
    },
    "Machinima": {},
    "Britain's Got Talent": {},
    "Spinnin' Records": {},
    "Manual do Mundo": {},
    "Smosh Games": {},
    "SQUEEZIE": {},
    "BIGBANG": {},
    "danisnotonfire": {},
    "Canal Nostalgia": {},
    "CinemaSins": {},
    "grav3yardgirl": {},
    "Jimmy Kimmel Live": {},
    "NBA": {
        "Steven Adams Hurting Rims in Miami | 12.27.16": {
            "google": "17407",
            "fb": "363k Views"
        }
    },
    "Bart Baker": {},
    "The Game Theorists": {},
    "CollegeHumor": {
        "What Could go Wrong with Our Dangerous Traps? (CHome Alone 5/5)": {
            "google": "396832",
            "fb": "103k Views"
        }
    },
    "Voc\u00ea Sabia?": {},
    "PewDiePie": {},
    "NORMAN": {},
    "rezendeevil": {},
    "LittleBabyBum \u00ae": {},
    "Vete a la Versh": {},
    "The Slow Mo Guys": {},
    "T-Series": {},
    "Werevertumorro": {},
    "shane": {}
}